pyramidpooling/__init__.py
pyramidpooling/pyramidpooling.py
pytorch_pyramid_pooling-0.1.0.dist-info/LICENSE
pytorch_pyramid_pooling-0.1.0.dist-info/METADATA
pytorch_pyramid_pooling-0.1.0.dist-info/WHEEL
pytorch_pyramid_pooling-0.1.0.dist-info/top_level.txt
pytorch_pyramid_pooling-0.1.0.dist-info/RECORD
