Metadata-Version: 2.1
Name: pytorch-pyramid-pooling
Version: 0.1.0
Summary: A PyTorch implementation of Spatial and Temporal Pyramid Pooling
Home-page: https://github.com/eric-musa/pytorch-pyramid-pooling
Author: Eric Musa
Author-email: eric.musa17@gmail.com
License: UNKNOWN
Project-URL: Bug Tracker, https://github.com/eric-musa/pytorch-pyramid-pooling/issues
Platform: UNKNOWN
Classifier: Programming Language :: Python :: 3
Classifier: License :: OSI Approved :: MIT License
Classifier: Operating System :: OS Independent
Requires-Python: >=3.6
License-File: LICENSE
